concrete/.python-version
concrete/__init__.py
concrete/__main__.py
concrete/abstract.py
concrete/operators.py
concrete/prompts.py
concrete/state.py
concrete/utils.py
concrete/webutils.py
concrete/clients/__init__.py
concrete/clients/base.py
concrete/clients/http.py
concrete/clients/openai.py
concrete/models/__init__.py
concrete/models/base.py
concrete/models/clients.py
concrete/models/messages.py
concrete/orchestrators/__init__.py
concrete/orchestrators/base.py
concrete/orchestrators/software_orchestrator.py
concrete/projects/__init__.py
concrete/projects/dag_project.py
concrete/projects/software_project.py
concrete/tools/__init__.py
concrete/tools/aws.py
concrete/tools/github.py
concrete/tools/http.py
concrete/tools/knowledge.py
concrete/tools/math.py
concrete/tools/meta.py
concrete/tools/utils.py
concrete_core-0.0.7.dist-info/METADATA
concrete_core-0.0.7.dist-info/WHEEL
concrete_core-0.0.7.dist-info/RECORD
