Metadata-Version: 2.3
Name: concrete-core
Version: 0.0.7
Summary: AI Agent Orchestration
Requires-Python: <4.0.0,>=3.11.9
Requires-Dist: pydantic>=2.0.0
Requires-Dist: python-dotenv>=1.0.0
Provides-Extra: auth
Requires-Dist: cryptography>=35.0.0; extra == 'auth'
Requires-Dist: fastapi>=0.105; extra == 'auth'
Requires-Dist: itsdangerous>=2.0.0; extra == 'auth'
Requires-Dist: pyjwt>=2.9.0; extra == 'auth'
Provides-Extra: google-auth
Requires-Dist: google-api-python-client>=2.0.0; extra == 'google-auth'
Requires-Dist: google-auth-oauthlib>=1.1.1; extra == 'google-auth'
Requires-Dist: google-auth>=2.25; extra == 'google-auth'
Provides-Extra: openai
Requires-Dist: openai>=1.40.0; extra == 'openai'
Provides-Extra: requests
Requires-Dist: requests>=2.0.0; extra == 'requests'
